b3j0f/__init__.py
b3j0f/middleware/url.py
b3j0f/middleware/core.py
b3j0f/middleware/version.py
b3j0f/middleware/cls.py
b3j0f/middleware/__init__.py
b3j0f/middleware/test/url.py
b3j0f/middleware/test/core.py
b3j0f/middleware/test/cls.py
b3j0f/middleware/test/__init__.py
b3j0f.middleware-0.0.11.dist-info/DESCRIPTION.rst
b3j0f.middleware-0.0.11.dist-info/RECORD
b3j0f.middleware-0.0.11.dist-info/metadata.json
b3j0f.middleware-0.0.11.dist-info/top_level.txt
b3j0f.middleware-0.0.11.dist-info/METADATA
b3j0f.middleware-0.0.11.dist-info/WHEEL
